dataverse_api/__init__.py
dataverse_api/_api.py
dataverse_api/dataverse.py
dataverse_api/entity.py
dataverse_api/errors.py
dataverse_api/schema.py
dataverse_api/metadata/__init__.py
dataverse_api/metadata/attributes.py
dataverse_api/metadata/base.py
dataverse_api/metadata/complex_properties.py
dataverse_api/metadata/entity.py
dataverse_api/metadata/enums.py
dataverse_api/metadata/helpers.py
dataverse_api/metadata/relationships.py
dataverse_api/utils/__init__.py
dataverse_api/utils/batching.py
dataverse_api/utils/data.py
dataverse_api/utils/labels.py
dataverse_api/utils/text.py
dataverse_api-1.3.2.dist-info/METADATA
dataverse_api-1.3.2.dist-info/WHEEL
dataverse_api-1.3.2.dist-info/licenses/LICENSE
dataverse_api-1.3.2.dist-info/RECORD
