Metadata-Version: 2.4
Name: dataverse-api
Version: 1.3.2
Summary: Abstraction layer for interacting with Microsoft Dataverse Web API using Python.
Project-URL: Repository, https://github.com/MarcusRisanger/Dataverse-API
Author-email: Marcus Risanger <69350948+MarcusRisanger@users.noreply.github.com>
License-File: LICENSE
Requires-Python: <4,>=3.11
Requires-Dist: narwhals>=1.45.0
Requires-Dist: pydantic<3,>=2.5.3
Requires-Dist: requests>=2.32.4
